Workbook

Sheet Pivot_Profitability_QoQ
A1: Category | B1: Revenue
A3: Metric_ID | B3: Metric_Name | C3: Sum of 1Q26 | D3: Sum of 2Q26 | E3: Sum of QoQ Growth %
A4: M021 | B4: Investment banking fees | C4: 2858 | D4: 3208 | E4: 0.12246326
A5: M022 | B5: Principal transactions | C5: 7987 | D5: 9007 | E5: 0.12770752
A6: M023 | B6: Lending- and deposit-related fees | C6: 2394 | D6: 2511 | E6: 0.04887218
A7: M024 | B7: Asset management fees | C7: 5515 | D7: 5658 | E7: 0.025929284
A8: M025 | B8: Commissions and other fees | C8: 2482 | D8: 2614 | E8: 0.053182917
A9: M026 | B9: Investment securities gains/(losses) | C9: 64 | D9: -395
A10: M027 | B10: Mortgage fees and related income | C10: 309 | D10: 336 | E10: 0.087378641
A11: M028 | B11: Card income | C11: 1190 | D11: 1348 | E11: 0.13277311
A12: M029 | B12: Other income | C12: 1671 | D12: 7549 | E12: 3.5176541
A13: M030 | B13: Total Net Revenue | C13: 49836 | D13: 57347 | E13: 0.15071434

Sheet Pivot_Expense_QoQ
A1: Category | B1: Expense
A3: Metric_ID | B3: Metric_Name | C3: Sum of 1Q26 | D3: Sum of 2Q26 | E3: Sum of QoQ Growth %
A4: M031 | B4: Compensation expense | C4: 15339 | D4: 15159 | E4: -0.011734794
A5: M032 | B5: Occupancy expense | C5: 1447 | D5: 1482 | E5: 0.024187975
A6: M033 | B6: Technology, communications and equipment expense | C6: 3021 | D6: 3107 | E6: 0.028467395
A7: M034 | B7: Professional and outside services | C7: 3483 | D7: 3855 | E7: 0.10680448
A8: M035 | B8: Marketing | C8: 1604 | D8: 1670 | E8: 0.041147132
A9: M036 | B9: Other expense | C9: 1956 | D9: 2043 | E9: 0.044478528
A10: M037 | B10: Total Noninterest Expense | C10: 26850 | D10: 27316 | E10: 0.01735568

Sheet Pivot_BalanceSheet_QoQ
A1: Category | B1: Revenue
A3: Metric_ID | B3: Metric_Name | C3: Sum of 2Q26 | D3: Sum of 1Q26 | E3: Sum of QoQ Growth %
A4: M021 | B4: Investment banking fees | C4: 3208 | D4: 2858 | E4: 0.12246326
A5: M022 | B5: Principal transactions | C5: 9007 | D5: 7987 | E5: 0.12770752
A6: M023 | B6: Lending- and deposit-related fees | C6: 2511 | D6: 2394 | E6: 0.04887218
A7: M024 | B7: Asset management fees | C7: 5658 | D7: 5515 | E7: 0.025929284
A8: M025 | B8: Commissions and other fees | C8: 2614 | D8: 2482 | E8: 0.053182917
A9: M026 | B9: Investment securities gains/(losses) | C9: -395 | D9: 64
A10: M027 | B10: Mortgage fees and related income | C10: 336 | D10: 309 | E10: 0.087378641
A11: M028 | B11: Card income | C11: 1348 | D11: 1190 | E11: 0.13277311
A12: M029 | B12: Other income | C12: 7549 | D12: 1671 | E12: 3.5176541
A13: M030 | B13: Total Net Revenue | C13: 57347 | D13: 49836 | E13: 0.15071434

Sheet Pivot_Credit_QoQ
A1: Category | B1: Revenue
A3: Metric_ID | B3: Metric_Name | C3: Sum of 1Q26 | D3: Sum of 2Q26 | E3: Sum of QoQ Growth %
A4: M021 | B4: Investment banking fees | C4: 2858 | D4: 3208 | E4: 0.12246326
A5: M022 | B5: Principal transactions | C5: 7987 | D5: 9007 | E5: 0.12770752
A6: M023 | B6: Lending- and deposit-related fees | C6: 2394 | D6: 2511 | E6: 0.04887218
A7: M024 | B7: Asset management fees | C7: 5515 | D7: 5658 | E7: 0.025929284
A8: M025 | B8: Commissions and other fees | C8: 2482 | D8: 2614 | E8: 0.053182917
A9: M026 | B9: Investment securities gains/(losses) | C9: 64 | D9: -395
A10: M027 | B10: Mortgage fees and related income | C10: 309 | D10: 336 | E10: 0.087378641
A11: M028 | B11: Card income | C11: 1190 | D11: 1348 | E11: 0.13277311
A12: M029 | B12: Other income | C12: 1671 | D12: 7549 | E12: 3.5176541
A13: M030 | B13: Total Net Revenue | C13: 49836 | D13: 57347 | E13: 0.15071434

Sheet Pivot_Employee_QoQ
A1: Category | B1: Revenue
A3: Metric_ID | B3: Metric_Name | C3: Sum of 1Q26 | D3: Sum of 2Q26 | E3: Sum of QoQ Growth %
A4: M021 | B4: Investment banking fees | C4: 2858 | D4: 3208 | E4: 0.12246326
A5: M022 | B5: Principal transactions | C5: 7987 | D5: 9007 | E5: 0.12770752
A6: M023 | B6: Lending- and deposit-related fees | C6: 2394 | D6: 2511 | E6: 0.04887218
A7: M024 | B7: Asset management fees | C7: 5515 | D7: 5658 | E7: 0.025929284
A8: M025 | B8: Commissions and other fees | C8: 2482 | D8: 2614 | E8: 0.053182917
A9: M026 | B9: Investment securities gains/(losses) | C9: 64 | D9: -395
A10: M027 | B10: Mortgage fees and related income | C10: 309 | D10: 336 | E10: 0.087378641
A11: M028 | B11: Card income | C11: 1190 | D11: 1348 | E11: 0.13277311
A12: M029 | B12: Other income | C12: 1671 | D12: 7549 | E12: 3.5176541
A13: M030 | B13: Total Net Revenue | C13: 49836 | D13: 57347 | E13: 0.15071434

Sheet Pivot_Revenue_QoQ
A1: Category | B1: Revenue | D1: Category | E1: Revenue
A3: Metric_Name | B3: Sum of QoQ Growth % | D3: Metric_Name | E3: Sum of QoQ Growth %
A4: Asset management fees | B4: 0.025929284 | D4: Other income | E4: 3.5176541
A5: Lending- and deposit-related fees | B5: 0.04887218 | D5: Total Net Revenue | E5: 0.15071434
A6: Commissions and other fees | B6: 0.053182917 | D6: Card income | E6: 0.13277311
A7: Mortgage fees and related income | B7: 0.087378641 | D7: Principal transactions | E7: 0.12770752
A8: Investment banking fees | B8: 0.12246326 | D8: Investment banking fees | E8: 0.12246326
A11: Metric_Name | B11: Sum of QoQ Growth %
A12: Other income | B12: 3.5176541
A13: Total Net Revenue | B13: 0.15071434
A14: Card income | B14: 0.13277311
A15: Principal transactions | B15: 0.12770752
A16: Investment banking fees | B16: 0.12246326
A17: Mortgage fees and related income | B17: 0.087378641
A18: Commissions and other fees | B18: 0.053182917
A19: Lending- and deposit-related fees | B19: 0.04887218
A20: Asset management fees | B20: 0.025929284
A21: Investment securities gains/(losses)

Sheet Pivot_Risk_QoQ
A1: Category | B1: Revenue
A3: Metric_ID | B3: Metric_Name | C3: Sum of 1Q26 | D3: Sum of 2Q26 | E3: Sum of QoQ Growth %
A4: M021 | B4: Investment banking fees | C4: 2858 | D4: 3208 | E4: 0.12246326
A5: M022 | B5: Principal transactions | C5: 7987 | D5: 9007 | E5: 0.12770752
A6: M023 | B6: Lending- and deposit-related fees | C6: 2394 | D6: 2511 | E6: 0.04887218
A7: M024 | B7: Asset management fees | C7: 5515 | D7: 5658 | E7: 0.025929284
A8: M025 | B8: Commissions and other fees | C8: 2482 | D8: 2614 | E8: 0.053182917
A9: M026 | B9: Investment securities gains/(losses) | C9: 64 | D9: -395
A10: M027 | B10: Mortgage fees and related income | C10: 309 | D10: 336 | E10: 0.087378641
A11: M028 | B11: Card income | C11: 1190 | D11: 1348 | E11: 0.13277311
A12: M029 | B12: Other income | C12: 1671 | D12: 7549 | E12: 3.5176541
A13: M030 | B13: Total Net Revenue | C13: 49836 | D13: 57347 | E13: 0.15071434

Sheet Pivot_Segment_QoQ
A1: Category | B1: Revenue
A3: Metric_ID | B3: Metric_Name | C3: Sum of QoQ Growth %
A4: M021 | B4: Investment banking fees | C4: 0.12246326
A5: M022 | B5: Principal transactions | C5: 0.12770752
A6: M023 | B6: Lending- and deposit-related fees | C6: 0.04887218
A7: M024 | B7: Asset management fees | C7: 0.025929284
A8: M025 | B8: Commissions and other fees | C8: 0.053182917
A9: M026 | B9: Investment securities gains/(losses)
A10: M027 | B10: Mortgage fees and related income | C10: 0.087378641
A11: M028 | B11: Card income | C11: 0.13277311
A12: M029 | B12: Other income | C12: 3.5176541
A13: M030 | B13: Total Net Revenue | C13: 0.15071434

Sheet QoQ_Summary
A1: Metric ID | B1: Metric Name | C1: 1Q26 | D1: 2Q26 | E1: QoQ Change % | F1: Row Reconciliation | H1: Control | I1: Result | J1: Revenue Metric | K1: QoQ Change % | M1: Revenue Metric | N1: QoQ Change % | P1: Revenue Metric | Q1: QoQ Change %
A2: M001 | B2: =INDEX(Raw_Data!$C$2:$C$38,MATCH($A2,Raw_Data!$A$2:$A$38,0)) -> Total Net Revenue | C2: =INDEX(Raw_Data!$H$2:$H$38,MATCH($A2,Raw_Data!$A$2:$A$38,0)) -> 49836 | D2: =INDEX(Raw_Data!$G$2:$G$38,MATCH($A2,Raw_Data!$A$2:$A$38,0)) -> 57347 | E2: =IF(OR(C2=0,SIGN(C2)<>SIGN(D2)),"NM",(D2-C2)/ABS(C2)) -> 0.15071434 | F2: =IF(AND(B2=INDEX(Raw_Data!$C$2:$C$38,MATCH($A2,Raw_Data!$A$2:$A$38,0)),C2=INDEX(Raw_Data!$H$2:$H$38,MATCH($A2,Raw_Data!$A$2:$A$38,0)),D2=INDEX(Raw_Data!$G$2:$G$38,MATCH($A2,Raw_Data!$A$2:$A$38,0))),"PASS","FAIL") -> PASS | H2: Reconciled rows | I2: =COUNTIF($F$2:$F$38,"PASS") -> 37 | J2: =INDEX($B$2:$B$38,MATCH("M021",$A$2:$A$38,0)) -> Investment banking fees | K2: =INDEX($E$2:$E$38,MATCH("M021",$A$2:$A$38,0)) -> 0.12246326 | M2: =INDEX($B$2:$B$38,MATCH("M024",$A$2:$A$38,0)) -> Asset management fees | N2: =INDEX($E$2:$E$38,MATCH("M024",$A$2:$A$38,0)) -> 0.025929284 | P2: =INDEX($B$2:$B$38,MATCH("M029",$A$2:$A$38,0)) -> Other income | Q2: =INDEX($E$2:$E$38,MATCH("M029",$A$2:$A$38,0)) -> 3.5176541
A3: M002 | B3: =INDEX(Raw_Data!$C$2:$C$38,MATCH($A3,Raw_Data!$A$2:$A$38,0)) -> Total Noninterest Expense | C3: =INDEX(Raw_Data!$H$2:$H$38,MATCH($A3,Raw_Data!$A$2:$A$38,0)) -> 26850 | D3: =INDEX(Raw_Data!$G$2:$G$38,MATCH($A3,Raw_Data!$A$2:$A$38,0)) -> 27316 | E3: =IF(OR(C3=0,SIGN(C3)<>SIGN(D3)),"NM",(D3-C3)/ABS(C3)) -> 0.01735568 | F3: =IF(AND(B3=INDEX(Raw_Data!$C$2:$C$38,MATCH($A3,Raw_Data!$A$2:$A$38,0)),C3=INDEX(Raw_Data!$H$2:$H$38,MATCH($A3,Raw_Data!$A$2:$A$38,0)),D3=INDEX(Raw_Data!$G$2:$G$38,MATCH($A3,Raw_Data!$A$2:$A$38,0))),"PASS","FAIL") -> PASS | H3: Expected rows | I3: =COUNTA(Raw_Data!$A$2:$A$38) -> 37 | J3: =INDEX($B$2:$B$38,MATCH("M022",$A$2:$A$38,0)) -> Principal transactions | K3: =INDEX($E$2:$E$38,MATCH("M022",$A$2:$A$38,0)) -> 0.12770752 | M3: =INDEX($B$2:$B$38,MATCH("M023",$A$2:$A$38,0)) -> Lending- and deposit-related fees | N3: =INDEX($E$2:$E$38,MATCH("M023",$A$2:$A$38,0)) -> 0.04887218 | P3: =INDEX($B$2:$B$38,MATCH("M030",$A$2:$A$38,0)) -> Total net revenue | Q3: =INDEX($E$2:$E$38,MATCH("M030",$A$2:$A$38,0)) -> 0.15071434
A4: M003 | B4: =INDEX(Raw_Data!$C$2:$C$38,MATCH($A4,Raw_Data!$A$2:$A$38,0)) -> Pre Provision Profit | C4: =INDEX(Raw_Data!$H$2:$H$38,MATCH($A4,Raw_Data!$A$2:$A$38,0)) -> 22986 | D4: =INDEX(Raw_Data!$G$2:$G$38,MATCH($A4,Raw_Data!$A$2:$A$38,0)) -> 30031 | E4: =IF(OR(C4=0,SIGN(C4)<>SIGN(D4)),"NM",(D4-C4)/ABS(C4)) -> 0.30649091 | F4: =IF(AND(B4=INDEX(Raw_Data!$C$2:$C$38,MATCH($A4,Raw_Data!$A$2:$A$38,0)),C4=INDEX(Raw_Data!$H$2:$H$38,MATCH($A4,Raw_Data!$A$2:$A$38,0)),D4=INDEX(Raw_Data!$G$2:$G$38,MATCH($A4,Raw_Data!$A$2:$A$38,0))),"PASS","FAIL") -> PASS | H4: Overall status | I4: =IF(AND(I2=I3,COUNTIF($F$2:$F$38,"FAIL")=0),"PASS","FAIL") -> PASS | J4: =INDEX($B$2:$B$38,MATCH("M023",$A$2:$A$38,0)) -> Lending- and deposit-related fees | K4: =INDEX($E$2:$E$38,MATCH("M023",$A$2:$A$38,0)) -> 0.04887218 | M4: =INDEX($B$2:$B$38,MATCH("M025",$A$2:$A$38,0)) -> Commissions and other fees | N4: =INDEX($E$2:$E$38,MATCH("M025",$A$2:$A$38,0)) -> 0.053182917 | P4: =INDEX($B$2:$B$38,MATCH("M028",$A$2:$A$38,0)) -> Card income | Q4: =INDEX($E$2:$E$38,MATCH("M028",$A$2:$A$38,0)) -> 0.13277311
A5: M004 | B5: =INDEX(Raw_Data!$C$2:$C$38,MATCH($A5,Raw_Data!$A$2:$A$38,0)) -> Provision for Credit Losses | C5: =INDEX(Raw_Data!$H$2:$H$38,MATCH($A5,Raw_Data!$A$2:$A$38,0)) -> 2507 | D5: =INDEX(Raw_Data!$G$2:$G$38,MATCH($A5,Raw_Data!$A$2:$A$38,0)) -> 2515 | E5: =IF(OR(C5=0,SIGN(C5)<>SIGN(D5)),"NM",(D5-C5)/ABS(C5)) -> 0.003191065 | F5: =IF(AND(B5=INDEX(Raw_Data!$C$2:$C$38,MATCH($A5,Raw_Data!$A$2:$A$38,0)),C5=INDEX(Raw_Data!$H$2:$H$38,MATCH($A5,Raw_Data!$A$2:$A$38,0)),D5=INDEX(Raw_Data!$G$2:$G$38,MATCH($A5,Raw_Data!$A$2:$A$38,0))),"PASS","FAIL") -> PASS | J5: =INDEX($B$2:$B$38,MATCH("M024",$A$2:$A$38,0)) -> Asset management fees | K5: =INDEX($E$2:$E$38,MATCH("M024",$A$2:$A$38,0)) -> 0.025929284 | M5: =INDEX($B$2:$B$38,MATCH("M027",$A$2:$A$38,0)) -> Mortgage fees and related income | N5: =INDEX($E$2:$E$38,MATCH("M027",$A$2:$A$38,0)) -> 0.087378641 | P5: =INDEX($B$2:$B$38,MATCH("M022",$A$2:$A$38,0)) -> Principal transactions | Q5: =INDEX($E$2:$E$38,MATCH("M022",$A$2:$A$38,0)) -> 0.12770752
A6: M005 | B6: =INDEX(Raw_Data!$C$2:$C$38,MATCH($A6,Raw_Data!$A$2:$A$38,0)) -> Net Income | C6: =INDEX(Raw_Data!$H$2:$H$38,MATCH($A6,Raw_Data!$A$2:$A$38,0)) -> 16494 | D6: =INDEX(Raw_Data!$G$2:$G$38,MATCH($A6,Raw_Data!$A$2:$A$38,0)) -> 21155 | E6: =IF(OR(C6=0,SIGN(C6)<>SIGN(D6)),"NM",(D6-C6)/ABS(C6)) -> 0.28258761 | F6: =IF(AND(B6=INDEX(Raw_Data!$C$2:$C$38,MATCH($A6,Raw_Data!$A$2:$A$38,0)),C6=INDEX(Raw_Data!$H$2:$H$38,MATCH($A6,Raw_Data!$A$2:$A$38,0)),D6=INDEX(Raw_Data!$G$2:$G$38,MATCH($A6,Raw_Data!$A$2:$A$38,0))),"PASS","FAIL") -> PASS | J6: =INDEX($B$2:$B$38,MATCH("M025",$A$2:$A$38,0)) -> Commissions and other fees | K6: =INDEX($E$2:$E$38,MATCH("M025",$A$2:$A$38,0)) -> 0.053182917
A7: M006 | B7: =INDEX(Raw_Data!$C$2:$C$38,MATCH($A7,Raw_Data!$A$2:$A$38,0)) -> Segment Net Revenue | C7: =INDEX(Raw_Data!$H$2:$H$38,MATCH($A7,Raw_Data!$A$2:$A$38,0)) -> 50536 | D7: =INDEX(Raw_Data!$G$2:$G$38,MATCH($A7,Raw_Data!$A$2:$A$38,0)) -> 58022 | E7: =IF(OR(C7=0,SIGN(C7)<>SIGN(D7)),"NM",(D7-C7)/ABS(C7)) -> 0.14813202 | F7: =IF(AND(B7=INDEX(Raw_Data!$C$2:$C$38,MATCH($A7,Raw_Data!$A$2:$A$38,0)),C7=INDEX(Raw_Data!$H$2:$H$38,MATCH($A7,Raw_Data!$A$2:$A$38,0)),D7=INDEX(Raw_Data!$G$2:$G$38,MATCH($A7,Raw_Data!$A$2:$A$38,0))),"PASS","FAIL") -> PASS | J7: =INDEX($B$2:$B$38,MATCH("M026",$A$2:$A$38,0)) -> Investment securities gains/(losses) | K7: =INDEX($E$2:$E$38,MATCH("M026",$A$2:$A$38,0)) -> NM
A8: M007 | B8: =INDEX(Raw_Data!$C$2:$C$38,MATCH($A8,Raw_Data!$A$2:$A$38,0)) -> Segment Noninterest Expense | C8: =INDEX(Raw_Data!$H$2:$H$38,MATCH($A8,Raw_Data!$A$2:$A$38,0)) -> 26850 | D8: =INDEX(Raw_Data!$G$2:$G$38,MATCH($A8,Raw_Data!$A$2:$A$38,0)) -> 27316 | E8: =IF(OR(C8=0,SIGN(C8)<>SIGN(D8)),"NM",(D8-C8)/ABS(C8)) -> 0.01735568 | F8: =IF(AND(B8=INDEX(Raw_Data!$C$2:$C$38,MATCH($A8,Raw_Data!$A$2:$A$38,0)),C8=INDEX(Raw_Data!$H$2:$H$38,MATCH($A8,Raw_Data!$A$2:$A$38,0)),D8=INDEX(Raw_Data!$G$2:$G$38,MATCH($A8,Raw_Data!$A$2:$A$38,0))),"PASS","FAIL") -> PASS | J8: =INDEX($B$2:$B$38,MATCH("M027",$A$2:$A$38,0)) -> Mortgage fees and related income | K8: =INDEX($E$2:$E$38,MATCH("M027",$A$2:$A$38,0)) -> 0.087378641
A9: M008 | B9: =INDEX(Raw_Data!$C$2:$C$38,MATCH($A9,Raw_Data!$A$2:$A$38,0)) -> Segment Pre-Provision Profit | C9: =INDEX(Raw_Data!$H$2:$H$38,MATCH($A9,Raw_Data!$A$2:$A$38,0)) -> 23686 | D9: =INDEX(Raw_Data!$G$2:$G$38,MATCH($A9,Raw_Data!$A$2:$A$38,0)) -> 30706 | E9: =IF(OR(C9=0,SIGN(C9)<>SIGN(D9)),"NM",(D9-C9)/ABS(C9)) -> 0.29637761 | F9: =IF(AND(B9=INDEX(Raw_Data!$C$2:$C$38,MATCH($A9,Raw_Data!$A$2:$A$38,0)),C9=INDEX(Raw_Data!$H$2:$H$38,MATCH($A9,Raw_Data!$A$2:$A$38,0)),D9=INDEX(Raw_Data!$G$2:$G$38,MATCH($A9,Raw_Data!$A$2:$A$38,0))),"PASS","FAIL") -> PASS | J9: =INDEX($B$2:$B$38,MATCH("M028",$A$2:$A$38,0)) -> Card income | K9: =INDEX($E$2:$E$38,MATCH("M028",$A$2:$A$38,0)) -> 0.13277311
A10: M009 | B10: =INDEX(Raw_Data!$C$2:$C$38,MATCH($A10,Raw_Data!$A$2:$A$38,0)) -> Segment Provision for Credit Losses | C10: =INDEX(Raw_Data!$H$2:$H$38,MATCH($A10,Raw_Data!$A$2:$A$38,0)) -> 2507 | D10: =INDEX(Raw_Data!$G$2:$G$38,MATCH($A10,Raw_Data!$A$2:$A$38,0)) -> 2515 | E10: =IF(OR(C10=0,SIGN(C10)<>SIGN(D10)),"NM",(D10-C10)/ABS(C10)) -> 0.003191065 | F10: =IF(AND(B10=INDEX(Raw_Data!$C$2:$C$38,MATCH($A10,Raw_Data!$A$2:$A$38,0)),C10=INDEX(Raw_Data!$H$2:$H$38,MATCH($A10,Raw_Data!$A$2:$A$38,0)),D10=INDEX(Raw_Data!$G$2:$G$38,MATCH($A10,Raw_Data!$A$2:$A$38,0))),"PASS","FAIL") -> PASS | J10: =INDEX($B$2:$B$38,MATCH("M029",$A$2:$A$38,0)) -> Other income | K10: =INDEX($E$2:$E$38,MATCH("M029",$A$2:$A$38,0)) -> 3.5176541
A11: M010 | B11: =INDEX(Raw_Data!$C$2:$C$38,MATCH($A11,Raw_Data!$A$2:$A$38,0)) -> Segment for net income | C11: =INDEX(Raw_Data!$H$2:$H$38,MATCH($A11,Raw_Data!$A$2:$A$38,0)) -> 16494 | D11: =INDEX(Raw_Data!$G$2:$G$38,MATCH($A11,Raw_Data!$A$2:$A$38,0)) -> 21155 | E11: =IF(OR(C11=0,SIGN(C11)<>SIGN(D11)),"NM",(D11-C11)/ABS(C11)) -> 0.28258761 | F11: =IF(AND(B11=INDEX(Raw_Data!$C$2:$C$38,MATCH($A11,Raw_Data!$A$2:$A$38,0)),C11=INDEX(Raw_Data!$H$2:$H$38,MATCH($A11,Raw_Data!$A$2:$A$38,0)),D11=INDEX(Raw_Data!$G$2:$G$38,MATCH($A11,Raw_Data!$A$2:$A$38,0))),"PASS","FAIL") -> PASS | J11: =INDEX($B$2:$B$38,MATCH("M030",$A$2:$A$38,0)) -> Total net revenue | K11: =INDEX($E$2:$E$38,MATCH("M030",$A$2:$A$38,0)) -> 0.15071434
A12: M011 | B12: =INDEX(Raw_Data!$C$2:$C$38,MATCH($A12,Raw_Data!$A$2:$A$38,0)) -> Total Assets | C12: =INDEX(Raw_Data!$H$2:$H$38,MATCH($A12,Raw_Data!$A$2:$A$38,0)) -> 4900475 | D12: =INDEX(Raw_Data!$G$2:$G$38,MATCH($A12,Raw_Data!$A$2:$A$38,0)) -> 5015069 | E12: =IF(OR(C12=0,SIGN(C12)<>SIGN(D12)),"NM",(D12-C12)/ABS(C12)) -> 0.023384264 | F12: =IF(AND(B12=INDEX(Raw_Data!$C$2:$C$38,MATCH($A12,Raw_Data!$A$2:$A$38,0)),C12=INDEX(Raw_Data!$H$2:$H$38,MATCH($A12,Raw_Data!$A$2:$A$38,0)),D12=INDEX(Raw_Data!$G$2:$G$38,MATCH($A12,Raw_Data!$A$2:$A$38,0))),"PASS","FAIL") -> PASS
A13: M012 | B13: =INDEX(Raw_Data!$C$2:$C$38,MATCH($A13,Raw_Data!$A$2:$A$38,0)) -> Total Loans | C13: =INDEX(Raw_Data!$H$2:$H$38,MATCH($A13,Raw_Data!$A$2:$A$38,0)) -> 1503520 | D13: =INDEX(Raw_Data!$G$2:$G$38,MATCH($A13,Raw_Data!$A$2:$A$38,0)) -> 1542462 | E13: =IF(OR(C13=0,SIGN(C13)<>SIGN(D13)),"NM",(D13-C13)/ABS(C13)) -> 0.025900553 | F13: =IF(AND(B13=INDEX(Raw_Data!$C$2:$C$38,MATCH($A13,Raw_Data!$A$2:$A$38,0)),C13=INDEX(Raw_Data!$H$2:$H$38,MATCH($A13,Raw_Data!$A$2:$A$38,0)),D13=INDEX(Raw_Data!$G$2:$G$38,MATCH($A13,Raw_Data!$A$2:$A$38,0))),"PASS","FAIL") -> PASS
A14: M013 | B14: =INDEX(Raw_Data!$C$2:$C$38,MATCH($A14,Raw_Data!$A$2:$A$38,0)) -> Total Deposits | C14: =INDEX(Raw_Data!$H$2:$H$38,MATCH($A14,Raw_Data!$A$2:$A$38,0)) -> 2675250 | D14: =INDEX(Raw_Data!$G$2:$G$38,MATCH($A14,Raw_Data!$A$2:$A$38,0)) -> 2713700 | E14: =IF(OR(C14=0,SIGN(C14)<>SIGN(D14)),"NM",(D14-C14)/ABS(C14)) -> 0.014372489 | F14: =IF(AND(B14=INDEX(Raw_Data!$C$2:$C$38,MATCH($A14,Raw_Data!$A$2:$A$38,0)),C14=INDEX(Raw_Data!$H$2:$H$38,MATCH($A14,Raw_Data!$A$2:$A$38,0)),D14=INDEX(Raw_Data!$G$2:$G$38,MATCH($A14,Raw_Data!$A$2:$A$38,0))),"PASS","FAIL") -> PASS
A15: M014 | B15: =INDEX(Raw_Data!$C$2:$C$38,MATCH($A15,Raw_Data!$A$2:$A$38,0)) -> Common Stockholders' Equity | C15: =INDEX(Raw_Data!$H$2:$H$38,MATCH($A15,Raw_Data!$A$2:$A$38,0)) -> 343993 | D15: =INDEX(Raw_Data!$G$2:$G$38,MATCH($A15,Raw_Data!$A$2:$A$38,0)) -> 353558 | E15: =IF(OR(C15=0,SIGN(C15)<>SIGN(D15)),"NM",(D15-C15)/ABS(C15)) -> 0.027805798 | F15: =IF(AND(B15=INDEX(Raw_Data!$C$2:$C$38,MATCH($A15,Raw_Data!$A$2:$A$38,0)),C15=INDEX(Raw_Data!$H$2:$H$38,MATCH($A15,Raw_Data!$A$2:$A$38,0)),D15=INDEX(Raw_Data!$G$2:$G$38,MATCH($A15,Raw_Data!$A$2:$A$38,0))),"PASS","FAIL") -> PASS
A16: M015 | B16: =INDEX(Raw_Data!$C$2:$C$38,MATCH($A16,Raw_Data!$A$2:$A$38,0)) -> Long-Term Debt | C16: =INDEX(Raw_Data!$H$2:$H$38,MATCH($A16,Raw_Data!$A$2:$A$38,0)) -> 448764 | D16: =INDEX(Raw_Data!$G$2:$G$38,MATCH($A16,Raw_Data!$A$2:$A$38,0)) -> 460523 | E16: =IF(OR(C16=0,SIGN(C16)<>SIGN(D16)),"NM",(D16-C16)/ABS(C16)) -> 0.026203082 | F16: =IF(AND(B16=INDEX(Raw_Data!$C$2:$C$38,MATCH($A16,Raw_Data!$A$2:$A$38,0)),C16=INDEX(Raw_Data!$H$2:$H$38,MATCH($A16,Raw_Data!$A$2:$A$38,0)),D16=INDEX(Raw_Data!$G$2:$G$38,MATCH($A16,Raw_Data!$A$2:$A$38,0))),"PASS","FAIL") -> PASS
A17: M016 | B17: =INDEX(Raw_Data!$C$2:$C$38,MATCH($A17,Raw_Data!$A$2:$A$38,0)) -> Loans-to-Deposits Ratio | C17: =INDEX(Raw_Data!$H$2:$H$38,MATCH($A17,Raw_Data!$A$2:$A$38,0)) -> 0.56 | D17: =INDEX(Raw_Data!$G$2:$G$38,MATCH($A17,Raw_Data!$A$2:$A$38,0)) -> 0.57 | E17: =IF(OR(C17=0,SIGN(C17)<>SIGN(D17)),"NM",(D17-C17)/ABS(C17)) -> 0.017857143 | F17: =IF(AND(B17=INDEX(Raw_Data!$C$2:$C$38,MATCH($A17,Raw_Data!$A$2:$A$38,0)),C17=INDEX(Raw_Data!$H$2:$H$38,MATCH($A17,Raw_Data!$A$2:$A$38,0)),D17=INDEX(Raw_Data!$G$2:$G$38,MATCH($A17,Raw_Data!$A$2:$A$38,0))),"PASS","FAIL") -> PASS
A18: M017 | B18: =INDEX(Raw_Data!$C$2:$C$38,MATCH($A18,Raw_Data!$A$2:$A$38,0)) -> Employees | C18: =INDEX(Raw_Data!$H$2:$H$38,MATCH($A18,Raw_Data!$A$2:$A$38,0)) -> 320079 | D18: =INDEX(Raw_Data!$G$2:$G$38,MATCH($A18,Raw_Data!$A$2:$A$38,0)) -> 320560 | E18: =IF(OR(C18=0,SIGN(C18)<>SIGN(D18)),"NM",(D18-C18)/ABS(C18)) -> 0.001502754 | F18: =IF(AND(B18=INDEX(Raw_Data!$C$2:$C$38,MATCH($A18,Raw_Data!$A$2:$A$38,0)),C18=INDEX(Raw_Data!$H$2:$H$38,MATCH($A18,Raw_Data!$A$2:$A$38,0)),D18=INDEX(Raw_Data!$G$2:$G$38,MATCH($A18,Raw_Data!$A$2:$A$38,0))),"PASS","FAIL") -> PASS
A19: M018 | B19: =INDEX(Raw_Data!$C$2:$C$38,MATCH($A19,Raw_Data!$A$2:$A$38,0)) -> Average VaR | C19: =INDEX(Raw_Data!$H$2:$H$38,MATCH($A19,Raw_Data!$A$2:$A$38,0)) -> 37 | D19: =INDEX(Raw_Data!$G$2:$G$38,MATCH($A19,Raw_Data!$A$2:$A$38,0)) -> 49 | E19: =IF(OR(C19=0,SIGN(C19)<>SIGN(D19)),"NM",(D19-C19)/ABS(C19)) -> 0.32432432 | F19: =IF(AND(B19=INDEX(Raw_Data!$C$2:$C$38,MATCH($A19,Raw_Data!$A$2:$A$38,0)),C19=INDEX(Raw_Data!$H$2:$H$38,MATCH($A19,Raw_Data!$A$2:$A$38,0)),D19=INDEX(Raw_Data!$G$2:$G$38,MATCH($A19,Raw_Data!$A$2:$A$38,0))),"PASS","FAIL") -> PASS
A20: M019 | B20: =INDEX(Raw_Data!$C$2:$C$38,MATCH($A20,Raw_Data!$A$2:$A$38,0)) -> Earnings-at-Risk +100 bps shift in rates | C20: =INDEX(Raw_Data!$H$2:$H$38,MATCH($A20,Raw_Data!$A$2:$A$38,0)) -> 1.9 | D20: =INDEX(Raw_Data!$G$2:$G$38,MATCH($A20,Raw_Data!$A$2:$A$38,0)) -> 1.8 | E20: =IF(OR(C20=0,SIGN(C20)<>SIGN(D20)),"NM",(D20-C20)/ABS(C20)) -> -0.052631579 | F20: =IF(AND(B20=INDEX(Raw_Data!$C$2:$C$38,MATCH($A20,Raw_Data!$A$2:$A$38,0)),C20=INDEX(Raw_Data!$H$2:$H$38,MATCH($A20,Raw_Data!$A$2:$A$38,0)),D20=INDEX(Raw_Data!$G$2:$G$38,MATCH($A20,Raw_Data!$A$2:$A$38,0))),"PASS","FAIL") -> PASS
A21: M020 | B21: =INDEX(Raw_Data!$C$2:$C$38,MATCH($A21,Raw_Data!$A$2:$A$38,0)) -> Earnings-at-Risk -100 bps shift in rates | C21: =INDEX(Raw_Data!$H$2:$H$38,MATCH($A21,Raw_Data!$A$2:$A$38,0)) -> -2.2 | D21: =INDEX(Raw_Data!$G$2:$G$38,MATCH($A21,Raw_Data!$A$2:$A$38,0)) -> -2.4 | E21: =IF(OR(C21=0,SIGN(C21)<>SIGN(D21)),"NM",(D21-C21)/ABS(C21)) -> -0.090909091 | F21: =IF(AND(B21=INDEX(Raw_Data!$C$2:$C$38,MATCH($A21,Raw_Data!$A$2:$A$38,0)),C21=INDEX(Raw_Data!$H$2:$H$38,MATCH($A21,Raw_Data!$A$2:$A$38,0)),D21=INDEX(Raw_Data!$G$2:$G$38,MATCH($A21,Raw_Data!$A$2:$A$38,0))),"PASS","FAIL") -> PASS
A22: M021 | B22: =INDEX(Raw_Data!$C$2:$C$38,MATCH($A22,Raw_Data!$A$2:$A$38,0)) -> Investment banking fees | C22: =INDEX(Raw_Data!$H$2:$H$38,MATCH($A22,Raw_Data!$A$2:$A$38,0)) -> 2858 | D22: =INDEX(Raw_Data!$G$2:$G$38,MATCH($A22,Raw_Data!$A$2:$A$38,0)) -> 3208 | E22: =IF(OR(C22=0,SIGN(C22)<>SIGN(D22)),"NM",(D22-C22)/ABS(C22)) -> 0.12246326 | F22: =IF(AND(B22=INDEX(Raw_Data!$C$2:$C$38,MATCH($A22,Raw_Data!$A$2:$A$38,0)),C22=INDEX(Raw_Data!$H$2:$H$38,MATCH($A22,Raw_Data!$A$2:$A$38,0)),D22=INDEX(Raw_Data!$G$2:$G$38,MATCH($A22,Raw_Data!$A$2:$A$38,0))),"PASS","FAIL") -> PASS
A23: M022 | B23: =INDEX(Raw_Data!$C$2:$C$38,MATCH($A23,Raw_Data!$A$2:$A$38,0)) -> Principal transactions | C23: =INDEX(Raw_Data!$H$2:$H$38,MATCH($A23,Raw_Data!$A$2:$A$38,0)) -> 7987 | D23: =INDEX(Raw_Data!$G$2:$G$38,MATCH($A23,Raw_Data!$A$2:$A$38,0)) -> 9007 | E23: =IF(OR(C23=0,SIGN(C23)<>SIGN(D23)),"NM",(D23-C23)/ABS(C23)) -> 0.12770752 | F23: =IF(AND(B23=INDEX(Raw_Data!$C$2:$C$38,MATCH($A23,Raw_Data!$A$2:$A$38,0)),C23=INDEX(Raw_Data!$H$2:$H$38,MATCH($A23,Raw_Data!$A$2:$A$38,0)),D23=INDEX(Raw_Data!$G$2:$G$38,MATCH($A23,Raw_Data!$A$2:$A$38,0))),"PASS","FAIL") -> PASS
... A38: M037 | B38: =INDEX(Raw_Data!$C$2:$C$38,MATCH($A38,Raw_Data!$A$2:$A$38,0)) -> Total noninterest expense | C38: =INDEX(Raw_Data!$H$2:$H$38,MATCH($A38,Raw_Data!$A$2:$A$38,0)) -> 26850 | D38: =INDEX(Raw_Data!$G$2:$G$38,MATCH($A38,Raw_Data!$A$2:$A$38,0)) -> 27316 | E38: =IF(OR(C38=0,SIGN(C38)<>SIGN(D38)),"NM",(D38-C38)/ABS(C38)) -> 0.01735568 | F38: =IF(AND(B38=INDEX(Raw_Data!$C$2:$C$38,MATCH($A38,Raw_Data!$A$2:$A$38,0)),C38=INDEX(Raw_Data!$H$2:$H$38,MATCH($A38,Raw_Data!$A$2:$A$38,0)),D38=INDEX(Raw_Data!$G$2:$G$38,MATCH($A38,Raw_Data!$A$2:$A$38,0))),"PASS","FAIL") -> PASS

Sheet Raw_Data
A1: Metric_ID | B1: Category | C1: Metric_Name | D1: Unit | E1: Basis | F1: Source_Page | G1: 2Q26 | H1: 1Q26 | I1: 4Q25 | J1: 3Q25 | K1: 2Q25
A2: M001 | B2: Profitability | C2: Total Net Revenue | D2: $mm | E2: Reported | F2: 2 | G2: 57347 | H2: 49836 | I2: 45798 | J2: 46427 | K2: 44912
A3: M002 | B3: Profitability | C3: Total Noninterest Expense | D3: $mm | E3: Reported | F3: 2 | G3: 27316 | H3: 26850 | I3: 23983 | J3: 24281 | K3: 23779
A4: M003 | B4: Profitability | C4: Pre Provision Profit | D4: $mm | E4: Reported | F4: 2 | G4: 30031 | H4: 22986 | I4: 21815 | J4: 22146 | K4: 21133
A5: M004 | B5: Credit | C5: Provision for Credit Losses | D5: $mm | E5: Reported | F5: 2 | G5: 2515 | H5: 2507 | I5: 4655 | J5: 3403 | K5: 2849
A6: M005 | B6: Profitability | C6: Net Income | D6: $mm | E6: Reported | F6: 2 | G6: 21155 | H6: 16494 | I6: 13025 | J6: 14393 | K6: 14987
A7: M006 | B7: Segment | C7: Segment Net Revenue | D7: $mm | E7: Managed | F7: 8 | G7: 58022 | H7: 50536 | I7: 46767 | J7: 47120 | K7: 45680
A8: M007 | B8: Segment | C8: Segment Noninterest Expense | D8: $mm | E8: Managed | F8: 8 | G8: 27316 | H8: 26850 | I8: 23983 | J8: 24281 | K8: 23779
A9: M008 | B9: Segment | C9: Segment Pre-Provision Profit | D9: $mm | E9: Managed | F9: 8 | G9: 30706 | H9: 23686 | I9: 22784 | J9: 22839 | K9: 21901
A10: M009 | B10: Segment | C10: Segment Provision for Credit Losses | D10: $mm | E10: Managed | F10: 8 | G10: 2515 | H10: 2507 | I10: 4655 | J10: 3403 | K10: 2849
A11: M010 | B11: Segment | C11: Segment for net income | D11: $mm | E11: Managed | F11: 8 | G11: 21155 | H11: 16494 | I11: 13025 | J11: 14393 | K11: 14987
A12: M011 | B12: Balance sheet | C12: Total Assets | D12: $mm | E12: Reported | F12: 3 | G12: 5015069 | H12: 4900475 | I12: 4424900 | J12: 4560205 | K12: 4552482
A13: M012 | B13: Balance sheet | C13: Total Loans | D13: $mm | E13: Reported | F13: 3 | G13: 1542462 | H13: 1503520 | I13: 1493429 | J13: 1453246 | K13: 1411992
... A38: M037 | B38: Expense | C38: Total noninterest expense | D38: $mm | E38: Reported | F38: 4 | G38: 27316 | H38: 26850 | I38: 23983 | J38: 24281 | K38: 23779

Sheet Dashboard
A1: JPMC Financial Performance Dashboard (QoQ Analysis)
F6: Metric | G6: Value
F7: Highest Revenue QoQ Change | G7: =MAX(QoQ_Summary!$K$2:$K$11) -> 3.5176541
F8: Median Revenue QoQ Change | G8: =MEDIAN(QoQ_Summary!$K$2:$K$11) -> 0.12246326
F9: Lowest Revenue QoQ Change | G9: =MIN(QoQ_Summary!$K$2:$K$11) -> 0.025929284

Sheet Source_Notes
A1: Source_Notes
A3: Source report | B3: JPMorganChase 2Q26 Earnings Supplement, released 14 July 2026.
A4: Primary URL | B4: https://www.jpmorganchase.com/content/dam/jpmc/jpmorgan-chase-and-co/investor-relations/documents/quarterly-earnings/2026/2nd-quarter/c9c097af-34e9-4aae-92d2-909a2ab7c083.pdf
A5: Filing copy | B5: https://www.sec.gov/Archives/edgar/data/19617/000162828026048078/a2q26erfex992supplement.htm
A6: Metric provenance | B6: Raw_Data retains source page, unit, basis and Metric_ID for every dashboard value.
A7: QoQ convention | B7: A positive-to-negative (or negative-to-positive) move is shown as N/M and excluded from revenue rankings.
